CHANGES.txt
LICENSE.txt
MANIFEST.in
README.txt
setup.cfg
setup.py
LRSignature/__init__.py
LRSignature/__main__.py
LRSignature/cmd.py
LRSignature/errors.py
LRSignature.egg-info/PKG-INFO
LRSignature.egg-info/SOURCES.txt
LRSignature.egg-info/dependency_links.txt
LRSignature.egg-info/requires.txt
LRSignature.egg-info/top_level.txt
LRSignature/bencode/BTL.py
LRSignature/bencode/__init__.py
LRSignature/sign/Sign.py
LRSignature/sign/__init__.py
LRSignature/tests/__init__.py
LRSignature/tests/config.cfg.sample
LRSignature/tests/signing.py
LRSignature/tests/utils.py
LRSignature/tests/verifying.py
LRSignature/util/__init__.py
LRSignature/verify/Verify.py
LRSignature/verify/__init__.py