Metadata-Version: 1.0
Name: LRSignature
Version: 0.1.14
Summary: Learning Registry resource data digital signature management
Home-page: https://github.com/jimklo/LRSignature
Author: Jim Klo
Author-email: jim.klo@sri.com
License: Apache 2.0 License
Platform: UNKNOWN
